{
    "Response 1": {
        "Roydon": "Guess what, I just got a new pet dog!",
        "Jacob": "That's awesome! What breed is it?"
    },
    "Response 2": {
        "Roydon": "It's a golden retriever, and he's the cutest thing ever!",
        "Jacob": "Golden retrievers are so friendly and loyal, you're going to have so much fun with him!"
    },
    "Response 3": {
        "Roydon": "I can't wait to take him for walks in the park and play fetch with him.",
        "Jacob": "He's going to love all the attention and exercise, you'll have a new best friend in no time!"
    },
    "Response 4": {
        "Roydon": "I already feel like we have a special bond, he follows me everywhere I go.",
        "Jacob": "That's the best feeling, knowing that your dog trusts and loves you unconditionally."
    },
    "Response 5": {
        "Roydon": "I feel like my heart is so full having him around, he brings so much joy into my life.",
        "Jacob": "Dogs have a way of filling our lives with happiness and love, it's truly a special connection."
    },
    "Response 6": {
        "Roydon": "I couldn't agree more, I feel like my new dog has completed my little family.",
        "Jacob": "It's amazing how pets have a way of making a house feel like a home, enjoy every moment with your furry friend!"
    },
    "Response 7": {
        "Jacob": "I definitely will, I can't imagine my life without him now."
    }
}